galileo_protect/__init__.py
galileo_protect/constants/__init__.py
galileo_protect/constants/invoke.py
galileo_protect/constants/routes.py
galileo_protect/health.py
galileo_protect/invocation.py
galileo_protect/langchain.py
galileo_protect/project.py
galileo_protect/py.typed
galileo_protect/schemas/__init__.py
galileo_protect/schemas/config.py
galileo_protect/schemas/rule.py
galileo_protect/schemas/stage.py
galileo_protect/stage.py
galileo_protect-1.0.0.dist-info/LICENSE
galileo_protect-1.0.0.dist-info/METADATA
galileo_protect-1.0.0.dist-info/WHEEL
galileo_protect-1.0.0.dist-info/RECORD
