Metadata-Version: 2.3
Name: galileo-protect
Version: 1.0.0
Summary: 🛡️ Secure your Generative AI applications with Galileo Protect!
License: Apache License
Author: Galileo Technologies Inc.
Author-email: team@rungalileo.io
Requires-Python: >=3.8.1
Classifier: Development Status :: 5 - Production/Stable
Classifier: Framework :: Pydantic
Classifier: License :: OSI Approved :: Apache Software License
Classifier: Framework :: IPython
Classifier: Framework :: Jupyter
Classifier: Framework :: Jupyter :: JupyterLab
Classifier: Intended Audience :: Developers
Classifier: Intended Audience :: Information Technology
Classifier: Intended Audience :: Science/Research
Classifier: Operating System :: OS Independent
Classifier: Programming Language :: ML
Classifier: Programming Language :: Python :: 3 :: Only
Classifier: Programming Language :: Python :: 3.8
Classifier: Programming Language :: Python :: 3.9
Classifier: Programming Language :: Python :: 3.10
Classifier: Programming Language :: Python :: 3.11
Classifier: Programming Language :: Python :: 3.12
Classifier: Programming Language :: Python :: 3.13
Classifier: Programming Language :: Python :: 3.14
Classifier: Topic :: Scientific/Engineering :: Artificial Intelligence
Classifier: Topic :: Software Development :: Libraries
Classifier: Topic :: Software Development :: Libraries :: Python Modules
Classifier: Typing :: Typed
Provides-Extra: all
Provides-Extra: langchain
Requires-Dist: galileo-core (>=3.36.0,<4.0.0)
Requires-Dist: langchain-core ; extra == "all"
Requires-Dist: langchain-core ; extra == "langchain"
Project-URL: Documentation, https://protect.docs.galileo.ai/
Project-URL: Homepage, https://www.galileo.ai/
Project-URL: Repository, https://github.com/rungalileo/protect
